{
    "class": "Bruges",
    "type": "Cruiser",
    "points": 84,
    "tonnage": "M",
    "base_size": 40,
    "profile": {
        "Thrust": 8,
        "Scan": 6,
        "Sig": 6,
        "Hull": 10,
        "ES": "4+",
        "KS": "3+",
        "BS": "-",
        "G": "1-2",
        "Special": []
    },
    "weapons": [
        {
            "Name": "Cobra Heavy Laser",
            "Arc": "FN",
            "Att": 4,
            "Lock": "3+",
            "DMG": 1,
            "Type": "E",
            "Special": [
                "Burnthrough-1",
                "Flash-1",
                "Focused"
            ]
        },
        {
            "Name": "Taipan Laser Turrets",
            "Arc": "F/S",
            "Att": 2,
            "Lock": "2+",
            "DMG": 1,
            "Type": "E",
            "Special": [
                "Scald-2"
            ]
        }
    ],
    "load": [],
    "equipment": [],
    "rules": [],
    "admiral_abilities": [],
    "famous_ships": [],
    "flavour": ""
}